odoo8_addon_account_move_line_stock_info-8.0.1.0.0-py2.7-nspkg.pth
odoo_addons/account_move_line_stock_info/__openerp__.py
odoo_addons/account_move_line_stock_info/__init__.py
odoo_addons/account_move_line_stock_info/README.rst
odoo_addons/account_move_line_stock_info/security/ir.model.access.csv
odoo_addons/account_move_line_stock_info/models/account_move_line.py
odoo_addons/account_move_line_stock_info/models/stock_move.py
odoo_addons/account_move_line_stock_info/models/stock_quant.py
odoo_addons/account_move_line_stock_info/models/__init__.py
odoo_addons/account_move_line_stock_info/views/stock_move_view.xml
odoo_addons/account_move_line_stock_info/views/account_move_line_view.xml
odoo_addons/account_move_line_stock_info/tests/__init__.py
odoo_addons/account_move_line_stock_info/tests/test_account_move_line_stock_move.py
odoo_addons/account_move_line_stock_info/static/description/icon.png
odoo8_addon_account_move_line_stock_info-8.0.1.0.0.dist-info/top_level.txt
odoo8_addon_account_move_line_stock_info-8.0.1.0.0.dist-info/WHEEL
odoo8_addon_account_move_line_stock_info-8.0.1.0.0.dist-info/RECORD
odoo8_addon_account_move_line_stock_info-8.0.1.0.0.dist-info/metadata.json
odoo8_addon_account_move_line_stock_info-8.0.1.0.0.dist-info/DESCRIPTION.rst
odoo8_addon_account_move_line_stock_info-8.0.1.0.0.dist-info/METADATA
odoo8_addon_account_move_line_stock_info-8.0.1.0.0.dist-info/namespace_packages.txt
